{
  "KOMUT_STUDIO_SAS": {
    "regime": "avant_affectation",
    "gate": true,
    "ecartFEC": 0,
    "ecartBilan": 0,
    "nonReconnus": 0,
    "ca": 578604.62,
    "rex": 229304.9,
    "rcai": 224128.52,
    "rexcep": -160,
    "rnet": 223968.52,
    "totalActif": 641708.11,
    "totalPassif": 641708.11,
    "capitauxPropres": 313742.46
  },
  "PLUS_DE_GOUT": {
    "regime": "avant_affectation",
    "gate": true,
    "ecartFEC": 0,
    "ecartBilan": 0,
    "nonReconnus": 0,
    "ca": 423551.6,
    "rex": -657.68,
    "rcai": -657.68,
    "rexcep": 1958.31,
    "rnet": 1103.63,
    "totalActif": 104705.06,
    "totalPassif": 104705.06,
    "capitauxPropres": 23764.73
  },
  "CITECOOP": {
    "regime": "avant_affectation",
    "gate": true,
    "ecartFEC": 0,
    "ecartBilan": 0,
    "nonReconnus": 0,
    "ca": 1247841.06,
    "rex": -309527.28,
    "rcai": -379117.39,
    "rexcep": -602,
    "rnet": -379719.39,
    "totalActif": 3659554.67,
    "totalPassif": 3659554.67,
    "capitauxPropres": -306490.19
  },
  "CLUB_MOBILITE": {
    "regime": "avant_affectation",
    "gate": true,
    "ecartFEC": 0,
    "ecartBilan": 0,
    "nonReconnus": 0,
    "ca": 262251.8,
    "rex": 5597.96,
    "rcai": 5898.97,
    "rexcep": -108,
    "rnet": 4315.97,
    "totalActif": 175692.71,
    "totalPassif": 175692.71,
    "capitauxPropres": 78532.79
  },
  "APA_DE_GEANT": {
    "regime": "avant_affectation",
    "gate": true,
    "ecartFEC": 0,
    "ecartBilan": 0,
    "nonReconnus": 0,
    "ca": 667840.46,
    "rex": 26303.68,
    "rcai": 24809.61,
    "rexcep": -250,
    "rnet": 59420.61,
    "totalActif": 323228.69,
    "totalPassif": 323228.69,
    "capitauxPropres": 231095.57
  }
}